{
  "code": 0,
  "msg": "success",
  "data": {
    "records": [
      {
        "number": 10,
        "salesName": "chenzaoqing",
        "createTime": 1539344615,
        "id": 23
      },
      {
        "number": 2,
        "salesName": "chenzaoqing",
        "createTime": 1539344658,
        "id": 24
      },
      {
        "number": 2,
        "salesName": "chenzaoqing",
        "createTime": 1539344658,
        "id": 2
      },
      {
        "number": 2,
        "salesName": "chenzaoqing",
        "createTime": 1539344658,
        "id": 3
      },
      {
        "number": 2,
        "salesName": "chenzaoqing",
        "createTime": 1539344658,
        "id": 4
      },
      {
        "number": 2,
        "salesName": "chenzaoqing",
        "createTime": 1539344658,
        "id": 25
      }
    ],
    "total": 2,
    "size": 2,
    "current": 1,
    "condition": {},
    "pages": 1
  }
}